protojit/__init__.py
protojit/protojit.py
protojit-0.2.dist-info/DESCRIPTION.rst
protojit-0.2.dist-info/METADATA
protojit-0.2.dist-info/RECORD
protojit-0.2.dist-info/WHEEL
protojit-0.2.dist-info/metadata.json
protojit-0.2.dist-info/top_level.txt
