Metadata-Version: 2.0
Name: protojit
Version: 0.2
Summary: Protobuf auto-generator
Home-page: https://github.com/willcrichton/protojit
Author: Will Crichton
Author-email: wcrichto@cs.stanford.edu
License: Apache 2.0
Platform: UNKNOWN
